media_toolkit/__init__.py
media_toolkit/core/__init__.py
media_toolkit/core/file_types.py
media_toolkit/core/content_detectors/__init__.py
media_toolkit/core/content_detectors/content_detector.py
media_toolkit/core/content_detectors/mimetype_content_detector.py
media_toolkit/core/content_detectors/numpy_content_detector.py
media_toolkit/core/content_detectors/puremagic_content_detector.py
media_toolkit/core/media_containers/__init__.py
media_toolkit/core/media_containers/i_media_container.py
media_toolkit/core/media_containers/media_dict.py
media_toolkit/core/media_containers/media_list.py
media_toolkit/core/media_files/__init__.py
media_toolkit/core/media_files/file_content_buffer.py
media_toolkit/core/media_files/file_conversion.py
media_toolkit/core/media_files/i_media_file.py
media_toolkit/core/media_files/image_file.py
media_toolkit/core/media_files/media_file.py
media_toolkit/core/media_files/universal_file.py
media_toolkit/core/media_files/audio/audio_file.py
media_toolkit/core/media_files/audio/audio_info.py
media_toolkit/core/media_files/audio/audio_stream.py
media_toolkit/core/media_files/video/__init__.py
media_toolkit/core/media_files/video/video_file.py
media_toolkit/core/media_files/video/video_info.py
media_toolkit/core/media_files/video/video_stream.py
media_toolkit/utils/auto_async.py
media_toolkit/utils/data_type_utils.py
media_toolkit/utils/dependency_requirements.py
media_toolkit/utils/download_helper.py
media_toolkit/utils/generator_wrapper.py
media_toolkit-0.2.21.dist-info/licenses/LICENSE
media_toolkit-0.2.21.dist-info/METADATA
media_toolkit-0.2.21.dist-info/WHEEL
media_toolkit-0.2.21.dist-info/top_level.txt
media_toolkit-0.2.21.dist-info/RECORD
