Metadata-Version: 2.4
Name: media-toolkit
Version: 0.2.21
Summary: Web-ready standardized file processing and serialization. Read, load and convert to standard file types with a common interface.
Author: SocAIty
License: MIT License
Project-URL: Repository, https://github.com/SocAIty/media-toolkit
Project-URL: Homepage, https://www.socaity.ai
Requires-Python: >=3.8
License-File: LICENSE
Requires-Dist: numpy>=1.18.0
Requires-Dist: puremagic>=1.29.0
Requires-Dist: opencv-python>=4.2
Requires-Dist: av>=15.1.0
Requires-Dist: tqdm
Requires-Dist: httpx
Provides-Extra: dev
Requires-Dist: pytest; extra == "dev"
Dynamic: license-file
